ruckig.cpython-38-i386-linux-gnu.so
lib/libruckig.a
lib/cmake/ruckig/ruckig-config-version.cmake
lib/cmake/ruckig/ruckig-config.cmake
lib/cmake/ruckig/ruckig-targets-release.cmake
lib/cmake/ruckig/ruckig-targets.cmake
ruckig-0.12.2.dist-info/WHEEL
ruckig-0.12.2.dist-info/entry_points.txt
ruckig-0.12.2.dist-info/RECORD
ruckig-0.12.2.dist-info/METADATA
ruckig-0.12.2.dist-info/licenses/LICENSE
share/ruckig/package.xml
