Metadata-Version: 2.1
Name: ruckig
Version: 0.12.2
Summary: Instantaneous Motion Generation for Robots and Machines.
Keywords: robotics trajectory-generation real-time jerk-constrained time-optimal
Author-Email: Lars Berscheid <lars.berscheid@ruckig.com>
License: MIT License
Classifier: Development Status :: 5 - Production/Stable
Classifier: Intended Audience :: Science/Research
Classifier: Topic :: Scientific/Engineering
Classifier: License :: OSI Approved :: MIT License
Classifier: Programming Language :: C++
Project-URL: Homepage, https://ruckig.com
Project-URL: Documentation, https://docs.ruckig.com
Project-URL: Repository, https://github.com/pantor/ruckig.git
Project-URL: Issues, https://github.com/pantor/ruckig/issues
Requires-Python: >=3.7
